pfylter/core.py
pfylter/strings.py
pfylter-0.3.0.dist-info/licenses/LICENSE
pfylter-0.3.0.dist-info/METADATA
pfylter-0.3.0.dist-info/WHEEL
pfylter-0.3.0.dist-info/top_level.txt
pfylter-0.3.0.dist-info/RECORD
