Metadata-Version: 2.4
Name: pfylter
Version: 0.3.0
Summary: A generic filtering framework using abstract composition
Author-email: Hugo López Fernández <hlfernandez@uvigo.gal>
License: MIT
Project-URL: Repository, https://github.com/hlfernandez/pfylter
Requires-Python: >=3.8
License-File: LICENSE
Dynamic: license-file
